{
  "runner_requested_spec": "latest",
  "runner_repo": "imadtg/TKUS-CE",
  "runner_resolved_tag": "v1.0.0",
  "runner_release_name": "v1.0.0",
  "runner_release_id": 296130286,
  "runner_release_url": "https://github.com/imadtg/TKUS-CE/releases/tag/v1.0.0",
  "runner_release_published_at": "2026-03-12T11:28:04Z",
  "runner_target_commitish": "main",
  "runner_asset_name": "tkus-ce-1.0.0.jar",
  "runner_asset_size_bytes": 789175,
  "runner_asset_download_url": "https://github.com/imadtg/TKUS-CE/releases/download/v1.0.0/tkus-ce-1.0.0.jar",
  "runner_downloaded_at_utc": "2026-03-12T11:37:12Z",
  "runner_output_jar": "/home/pc/Desktop/tkus-ce-optuna/artifacts/optuna/tkus-ce-release-check-single-20260312/runner/tkus-ce-runner.jar",
  "runner_sha256": "26e23583a8469582fe6e9d5f533e2a8480d897477e06cda5f1b12d93ac9fa1f7",
  "runner_sha256_from_release": "26e23583a8469582fe6e9d5f533e2a8480d897477e06cda5f1b12d93ac9fa1f7",
  "runner_sha256_verified": true,
  "runner_version": "1.0.0",
  "runner_release_channel": "release",
  "runner_git_ref": "v1.0.0",
  "runner_git_sha": "73692dc96b5b487983c7af6915c33f6df41f5d7c",
  "runner_repository": "https://github.com/imadtg/TKUS-CE",
  "runner_built_at_utc": "2026-03-12T11:30:04Z",
  "release": {
    "url": "https://api.github.com/repos/imadtg/TKUS-CE/releases/296130286",
    "assets_url": "https://api.github.com/repos/imadtg/TKUS-CE/releases/296130286/assets",
    "upload_url": "https://uploads.github.com/repos/imadtg/TKUS-CE/releases/296130286/assets{?name,label}",
    "html_url": "https://github.com/imadtg/TKUS-CE/releases/tag/v1.0.0",
    "id": 296130286,
    "author": {
      "login": "github-actions[bot]",
      "id": 41898282,
      "node_id": "MDM6Qm90NDE4OTgyODI=",
      "avatar_url": "https://avatars.githubusercontent.com/in/15368?v=4",
      "gravatar_id": "",
      "url": "https://api.github.com/users/github-actions%5Bbot%5D",
      "html_url": "https://github.com/apps/github-actions",
      "followers_url": "https://api.github.com/users/github-actions%5Bbot%5D/followers",
      "following_url": "https://api.github.com/users/github-actions%5Bbot%5D/following{/other_user}",
      "gists_url": "https://api.github.com/users/github-actions%5Bbot%5D/gists{/gist_id}",
      "starred_url": "https://api.github.com/users/github-actions%5Bbot%5D/starred{/owner}{/repo}",
      "subscriptions_url": "https://api.github.com/users/github-actions%5Bbot%5D/subscriptions",
      "organizations_url": "https://api.github.com/users/github-actions%5Bbot%5D/orgs",
      "repos_url": "https://api.github.com/users/github-actions%5Bbot%5D/repos",
      "events_url": "https://api.github.com/users/github-actions%5Bbot%5D/events{/privacy}",
      "received_events_url": "https://api.github.com/users/github-actions%5Bbot%5D/received_events",
      "type": "Bot",
      "user_view_type": "public",
      "site_admin": false
    },
    "node_id": "RE_kwDOQSUMks4Rppbu",
    "tag_name": "v1.0.0",
    "target_commitish": "main",
    "name": "v1.0.0",
    "draft": false,
    "immutable": false,
    "prerelease": false,
    "created_at": "2026-03-12T11:26:44Z",
    "updated_at": "2026-03-12T11:30:16Z",
    "published_at": "2026-03-12T11:28:04Z",
    "assets": [
      {
        "url": "https://api.github.com/repos/imadtg/TKUS-CE/releases/assets/372287255",
        "id": 372287255,
        "node_id": "RA_kwDOQSUMks4WMKcX",
        "name": "tkus-ce-1.0.0.jar",
        "label": "",
        "uploader": {
          "login": "github-actions[bot]",
          "id": 41898282,
          "node_id": "MDM6Qm90NDE4OTgyODI=",
          "avatar_url": "https://avatars.githubusercontent.com/in/15368?v=4",
          "gravatar_id": "",
          "url": "https://api.github.com/users/github-actions%5Bbot%5D",
          "html_url": "https://github.com/apps/github-actions",
          "followers_url": "https://api.github.com/users/github-actions%5Bbot%5D/followers",
          "following_url": "https://api.github.com/users/github-actions%5Bbot%5D/following{/other_user}",
          "gists_url": "https://api.github.com/users/github-actions%5Bbot%5D/gists{/gist_id}",
          "starred_url": "https://api.github.com/users/github-actions%5Bbot%5D/starred{/owner}{/repo}",
          "subscriptions_url": "https://api.github.com/users/github-actions%5Bbot%5D/subscriptions",
          "organizations_url": "https://api.github.com/users/github-actions%5Bbot%5D/orgs",
          "repos_url": "https://api.github.com/users/github-actions%5Bbot%5D/repos",
          "events_url": "https://api.github.com/users/github-actions%5Bbot%5D/events{/privacy}",
          "received_events_url": "https://api.github.com/users/github-actions%5Bbot%5D/received_events",
          "type": "Bot",
          "user_view_type": "public",
          "site_admin": false
        },
        "content_type": "application/java-archive",
        "state": "uploaded",
        "size": 789175,
        "digest": "sha256:26e23583a8469582fe6e9d5f533e2a8480d897477e06cda5f1b12d93ac9fa1f7",
        "download_count": 0,
        "created_at": "2026-03-12T11:30:16Z",
        "updated_at": "2026-03-12T11:30:16Z",
        "browser_download_url": "https://github.com/imadtg/TKUS-CE/releases/download/v1.0.0/tkus-ce-1.0.0.jar"
      },
      {
        "url": "https://api.github.com/repos/imadtg/TKUS-CE/releases/assets/372287254",
        "id": 372287254,
        "node_id": "RA_kwDOQSUMks4WMKcW",
        "name": "tkus-ce-1.0.0.jar.build.json",
        "label": "",
        "uploader": {
          "login": "github-actions[bot]",
          "id": 41898282,
          "node_id": "MDM6Qm90NDE4OTgyODI=",
          "avatar_url": "https://avatars.githubusercontent.com/in/15368?v=4",
          "gravatar_id": "",
          "url": "https://api.github.com/users/github-actions%5Bbot%5D",
          "html_url": "https://github.com/apps/github-actions",
          "followers_url": "https://api.github.com/users/github-actions%5Bbot%5D/followers",
          "following_url": "https://api.github.com/users/github-actions%5Bbot%5D/following{/other_user}",
          "gists_url": "https://api.github.com/users/github-actions%5Bbot%5D/gists{/gist_id}",
          "starred_url": "https://api.github.com/users/github-actions%5Bbot%5D/starred{/owner}{/repo}",
          "subscriptions_url": "https://api.github.com/users/github-actions%5Bbot%5D/subscriptions",
          "organizations_url": "https://api.github.com/users/github-actions%5Bbot%5D/orgs",
          "repos_url": "https://api.github.com/users/github-actions%5Bbot%5D/repos",
          "events_url": "https://api.github.com/users/github-actions%5Bbot%5D/events{/privacy}",
          "received_events_url": "https://api.github.com/users/github-actions%5Bbot%5D/received_events",
          "type": "Bot",
          "user_view_type": "public",
          "site_admin": false
        },
        "content_type": "application/json",
        "state": "uploaded",
        "size": 390,
        "digest": "sha256:95dcc95e5f7b2a56d03e15a1d4ad5f6d7b7f616ded1577bd587fde0f4601e802",
        "download_count": 0,
        "created_at": "2026-03-12T11:30:16Z",
        "updated_at": "2026-03-12T11:30:16Z",
        "browser_download_url": "https://github.com/imadtg/TKUS-CE/releases/download/v1.0.0/tkus-ce-1.0.0.jar.build.json"
      },
      {
        "url": "https://api.github.com/repos/imadtg/TKUS-CE/releases/assets/372287253",
        "id": 372287253,
        "node_id": "RA_kwDOQSUMks4WMKcV",
        "name": "tkus-ce-1.0.0.jar.sha256",
        "label": "",
        "uploader": {
          "login": "github-actions[bot]",
          "id": 41898282,
          "node_id": "MDM6Qm90NDE4OTgyODI=",
          "avatar_url": "https://avatars.githubusercontent.com/in/15368?v=4",
          "gravatar_id": "",
          "url": "https://api.github.com/users/github-actions%5Bbot%5D",
          "html_url": "https://github.com/apps/github-actions",
          "followers_url": "https://api.github.com/users/github-actions%5Bbot%5D/followers",
          "following_url": "https://api.github.com/users/github-actions%5Bbot%5D/following{/other_user}",
          "gists_url": "https://api.github.com/users/github-actions%5Bbot%5D/gists{/gist_id}",
          "starred_url": "https://api.github.com/users/github-actions%5Bbot%5D/starred{/owner}{/repo}",
          "subscriptions_url": "https://api.github.com/users/github-actions%5Bbot%5D/subscriptions",
          "organizations_url": "https://api.github.com/users/github-actions%5Bbot%5D/orgs",
          "repos_url": "https://api.github.com/users/github-actions%5Bbot%5D/repos",
          "events_url": "https://api.github.com/users/github-actions%5Bbot%5D/events{/privacy}",
          "received_events_url": "https://api.github.com/users/github-actions%5Bbot%5D/received_events",
          "type": "Bot",
          "user_view_type": "public",
          "site_admin": false
        },
        "content_type": "application/octet-stream",
        "state": "uploaded",
        "size": 123,
        "digest": "sha256:d6e3e6e2c2ed0a00909425688ebfa20ac512b05d5e912b760aad2892f86ddb49",
        "download_count": 0,
        "created_at": "2026-03-12T11:30:16Z",
        "updated_at": "2026-03-12T11:30:16Z",
        "browser_download_url": "https://github.com/imadtg/TKUS-CE/releases/download/v1.0.0/tkus-ce-1.0.0.jar.sha256"
      }
    ],
    "tarball_url": "https://api.github.com/repos/imadtg/TKUS-CE/tarball/v1.0.0",
    "zipball_url": "https://api.github.com/repos/imadtg/TKUS-CE/zipball/v1.0.0",
    "body": "# 1.0.0 (2026-03-12)\n\n\n* feat!: create CLI interface ([d3374ea](https://github.com/imadtg/TKUS-CE/commit/d3374ea0efe9d869e9b013934626f5b030cdcb4b))\n\n\n### Bug Fixes\n\n* add fetch-depth: 0 and fetch-tags: true to benchmark action checkout ([ca797ad](https://github.com/imadtg/TKUS-CE/commit/ca797ad511b432045b55735ffea5c878ed73de9d))\n* add permissions for PR comments ([b1d7d54](https://github.com/imadtg/TKUS-CE/commit/b1d7d54ea5043de1af491584a7b51fbedaae44d8))\n* allow selecting the last element in initial population ([ffb2e59](https://github.com/imadtg/TKUS-CE/commit/ffb2e5988bcaaf3a31bf7da2605f1faf145baa8a))\n* allow selecting the last element in initial population ([#24](https://github.com/imadtg/TKUS-CE/issues/24)) ([52ec2fe](https://github.com/imadtg/TKUS-CE/commit/52ec2fe870fde5e73462f703bff3d3db752d3847))\n* cast to long using some gymnastics ([9fd608c](https://github.com/imadtg/TKUS-CE/commit/9fd608cbda65c08ab3060242f3d3bf2627438856))\n* check if itemset or sequence are empty before inserting them ([9ca7d7e](https://github.com/imadtg/TKUS-CE/commit/9ca7d7e45873a18569cc48b5e8e3e4bd42f3827c))\n* check if itemset or sequence are empty before inserting them ([#2](https://github.com/imadtg/TKUS-CE/issues/2)) ([c4c4e29](https://github.com/imadtg/TKUS-CE/commit/c4c4e295f50ce18d75a3cb7fbed22155d172f359))\n* checkout private action repo with PAT ([485beb4](https://github.com/imadtg/TKUS-CE/commit/485beb48335d0958d3ef9535da2b3d7a56ce791d))\n* **ci:** use correct dataset filename in benchmark workflow ([477b7fe](https://github.com/imadtg/TKUS-CE/commit/477b7fe5c774465ed4b54c58da9f5a8e325f6c12))\n* clone the bitset instead of sharing the reference ([10e1b86](https://github.com/imadtg/TKUS-CE/commit/10e1b86ce98a56c532ecfaba7f72aab61353a2a4))\n* correct the itemsetContrib matching logic ([a148035](https://github.com/imadtg/TKUS-CE/commit/a1480353112390136757fdc4a6e212fcd0b44ecf))\n* correct the itemsetContrib matching logic ([#19](https://github.com/imadtg/TKUS-CE/issues/19)) ([7e3c6dc](https://github.com/imadtg/TKUS-CE/commit/7e3c6dc2967b35f4715d2df1b66f6b053dba6f16))\n* correct the sampling to use a considered item ([8089df7](https://github.com/imadtg/TKUS-CE/commit/8089df763f6de5cc6c83d7461a43eaf7c8ec7c71))\n* correct the sampling to use a considered item ([#15](https://github.com/imadtg/TKUS-CE/issues/15)) ([f967ed3](https://github.com/imadtg/TKUS-CE/commit/f967ed364949524fff8b72b0f3cebd8801d061a3))\n* correctly check whether a considered item exists ([05e6f5f](https://github.com/imadtg/TKUS-CE/commit/05e6f5f42c57f3cf79bcbb8a49d484f41f56d710))\n* correctly check whether a considered item exists ([#16](https://github.com/imadtg/TKUS-CE/issues/16)) ([aa44e5f](https://github.com/imadtg/TKUS-CE/commit/aa44e5fbda49be5b22ae59d5c94a35a512910b0d))\n* drop vestigial version info, to be readded through conventional commits log ([66a08f9](https://github.com/imadtg/TKUS-CE/commit/66a08f9e22a6d8eac87b390c4167670ea2537999))\n* ensure insertTopList always inserts ([b8ca110](https://github.com/imadtg/TKUS-CE/commit/b8ca1102a7cc4b229f9ec8c1508a8e4136f0c430))\n* ensure insertTopList always inserts ([#9](https://github.com/imadtg/TKUS-CE/issues/9)) ([72c08a3](https://github.com/imadtg/TKUS-CE/commit/72c08a332c55653f50e0523a22cdf694d401bb86))\n* ensure next is a valid index ([9459579](https://github.com/imadtg/TKUS-CE/commit/9459579480d108d5c9e3159530ae1c02c6680e61))\n* ensure next is a valid index ([#11](https://github.com/imadtg/TKUS-CE/issues/11)) ([a768535](https://github.com/imadtg/TKUS-CE/commit/a7685357dc004ab1d30550f52101523a394c0402))\n* ensure there are no duplicates in `husTopKBA` ([dbbd45a](https://github.com/imadtg/TKUS-CE/commit/dbbd45a79e202e92beccda7d941b27ebb0f70e60))\n* ensure there are no duplicates in `husTopKBA` ([#20](https://github.com/imadtg/TKUS-CE/issues/20)) ([c582029](https://github.com/imadtg/TKUS-CE/commit/c582029700b938c17b6af881424a260dd9e20586))\n* fix off by oneish error ([06e4dc7](https://github.com/imadtg/TKUS-CE/commit/06e4dc73a97bdd3e126c6855b526f429c7361511))\n* fix off by oneish error ([#6](https://github.com/imadtg/TKUS-CE/issues/6)) ([d032456](https://github.com/imadtg/TKUS-CE/commit/d03245696aee36099f7d99b5cfab66f4a512bb2c))\n* fix some things to work with sequences, generate pop is in a bad shape though... ([c44c3ab](https://github.com/imadtg/TKUS-CE/commit/c44c3ab55dc7fe4777327293c28146542f319f1a))\n* fix the logic for sequenceContrib ([002858a](https://github.com/imadtg/TKUS-CE/commit/002858a59fcce99ebaa1a7049211a567b67e1fcc))\n* fix the logic for sequenceContrib ([#13](https://github.com/imadtg/TKUS-CE/issues/13)) ([83b089c](https://github.com/imadtg/TKUS-CE/commit/83b089cf74bf3979667d26e447a21d43ff64699b))\n* fix typo ([92b4f82](https://github.com/imadtg/TKUS-CE/commit/92b4f82c646fa3d58593fe2596488ee0a773e8c4))\n* fix typo ([#22](https://github.com/imadtg/TKUS-CE/issues/22)) ([8d55d40](https://github.com/imadtg/TKUS-CE/commit/8d55d40a5f9bb3fd543d9b425d0513543288f2bc))\n* flush `population` on each iteration ([0703cf9](https://github.com/imadtg/TKUS-CE/commit/0703cf99d775b05a2c74e6b689b05b74a2999ccd))\n* flush `population` on each iteration ([#17](https://github.com/imadtg/TKUS-CE/issues/17)) ([89dd482](https://github.com/imadtg/TKUS-CE/commit/89dd4828fbf77902cc11776288abe740bbc72ce4))\n* force k to be 1 or more ([507b309](https://github.com/imadtg/TKUS-CE/commit/507b309fbd7b921f0157da0f17e1900d573ae019))\n* index into items list correctly ([898c1a8](https://github.com/imadtg/TKUS-CE/commit/898c1a8b4d3c9b9dc3dc7e13e7a5230d7bfb9b5e))\n* index into items list correctly ([#8](https://github.com/imadtg/TKUS-CE/issues/8)) ([306d6e9](https://github.com/imadtg/TKUS-CE/commit/306d6e96108076991b19e7614b64db4f2e6f4cf8))\n* index items correctly ([bd514c0](https://github.com/imadtg/TKUS-CE/commit/bd514c0f7068054efbf8acc260be93d8b264725f))\n* index items correctly ([#7](https://github.com/imadtg/TKUS-CE/issues/7)) ([65c8b5e](https://github.com/imadtg/TKUS-CE/commit/65c8b5e48578ce81ee1ab5dcbbb7e2d4d08fd4fa))\n* initialize consideredItems ([9830e0f](https://github.com/imadtg/TKUS-CE/commit/9830e0f4fd7390be25a0c539860d563ddce65e60))\n* make it working with jbang ([ec64b66](https://github.com/imadtg/TKUS-CE/commit/ec64b66aaf39da554e8e88772a4b785524917bfb))\n* make repairAndReturnSupportIndices work with sequences ([84887e5](https://github.com/imadtg/TKUS-CE/commit/84887e52a549ceb8a5cc1ec8ae44de22ca6c8462))\n* make sampleParticle work with sequences (simple singleton sequence of one itemset generalization for now) ([fa38689](https://github.com/imadtg/TKUS-CE/commit/fa3868966797d89ec2dfcbea33c21a07e64b9eca))\n* make the insert function work with sequences ([81984e7](https://github.com/imadtg/TKUS-CE/commit/81984e7ef27819aed3029053644ab6cff3f38473))\n* make the test use tkusce and a proper sequence database as default ([7812628](https://github.com/imadtg/TKUS-CE/commit/7812628cd6e9a7f246af1772bb5bb522314a3ebf))\n* make these work with sequences ([5952de3](https://github.com/imadtg/TKUS-CE/commit/5952de3ffcb9a785f10983be068afa7ff0e691e2))\n* make tkusce work with sequences ([#1](https://github.com/imadtg/TKUS-CE/issues/1)) ([03ae750](https://github.com/imadtg/TKUS-CE/commit/03ae750826a202e49a330fd137432a9c49ba32d8))\n* port the majority of the CE code to work with sequences ([3efbeda](https://github.com/imadtg/TKUS-CE/commit/3efbedada4b89d71a35f0f738b78e3a18c85e364))\n* remove unused imports ([7d96734](https://github.com/imadtg/TKUS-CE/commit/7d9673463abffcf835774789e85bc139156b5dc0))\n* remove unused imports ([#30](https://github.com/imadtg/TKUS-CE/issues/30)) ([30bffdc](https://github.com/imadtg/TKUS-CE/commit/30bffdc6bc979c61c737d595d31283e4f77c0f90))\n* remove vestigial changes only done to trigger CI ([8fb5a45](https://github.com/imadtg/TKUS-CE/commit/8fb5a452aa6c68e7d5729159db9e57e7ec93d0b8))\n* replace mention of huiSets to husSets in this comment ([9ac1459](https://github.com/imadtg/TKUS-CE/commit/9ac1459ba6cb63d08ae6377514a3f6942ceb759f))\n* throw on empty itemset in candidate to be repaired ([33f5ee2](https://github.com/imadtg/TKUS-CE/commit/33f5ee29869d1114a99a081f3e46fe23fb7a5328))\n* throw on empty itemset in candidate to be repaired ([#14](https://github.com/imadtg/TKUS-CE/issues/14)) ([d9a7e1e](https://github.com/imadtg/TKUS-CE/commit/d9a7e1ece130c3bf5c98aa5d7e2fa4736c92246b))\n* typo ([130baf1](https://github.com/imadtg/TKUS-CE/commit/130baf1927eb526afd653a5f7c5bfb977661625e))\n\n\n### Features\n\n* add --verbose flag to print stack traces ([1e81358](https://github.com/imadtg/TKUS-CE/commit/1e813586c4162a2e9c79f0040f347fe08ac3d303))\n* add AGENTS.md ([a0e0414](https://github.com/imadtg/TKUS-CE/commit/a0e0414fd1ced614d86b26935b26af2385754843))\n* add benchmark workflow for PR performance comparison ([dcec889](https://github.com/imadtg/TKUS-CE/commit/dcec889e1ae4932026f83e5915023a4d4b53b51d))\n* add iteration metrics ([4f46a44](https://github.com/imadtg/TKUS-CE/commit/4f46a44c68969bbd727e30424f93b2dbf6597d38))\n* be robust to missing parameters or params.yaml file ([3fcfb1d](https://github.com/imadtg/TKUS-CE/commit/3fcfb1d20243dfa1f85fd91b188a3a69edafb481))\n* be robust to missing parameters or params.yaml file ([#25](https://github.com/imadtg/TKUS-CE/issues/25)) ([906824d](https://github.com/imadtg/TKUS-CE/commit/906824dd5814244edd7ecefa5c44d0b449baf3a1))\n* **ci:** add benchmark-ref and scope inputs to workflow_dispatch ([236de54](https://github.com/imadtg/TKUS-CE/commit/236de54c3a81989bc23ba334eb89434460ca951a))\n* initial commit ([2c4f381](https://github.com/imadtg/TKUS-CE/commit/2c4f3812a0e34f7db7ea64f0037ec42665fb6679))\n* more sensible default hyperparams ([c4047b8](https://github.com/imadtg/TKUS-CE/commit/c4047b8c8755c05f478b2af9797a00b62929da17))\n* move probability model logic out of the algorithm code and abstract it away ([391d7a2](https://github.com/imadtg/TKUS-CE/commit/391d7a2bc8bf831deeaf447b126d640bb7bdf3f1))\n* move probability model logic out of the algorithm code and abstract it away ([#3](https://github.com/imadtg/TKUS-CE/issues/3)) ([310c58b](https://github.com/imadtg/TKUS-CE/commit/310c58bd45123e63b1794b5163a206affcbb977a))\n* n-gram model ([#32](https://github.com/imadtg/TKUS-CE/issues/32)) ([4c6ec6f](https://github.com/imadtg/TKUS-CE/commit/4c6ec6fb3eb1637728a35bbf91693be6446e20fb))\n* **release:** automate portable jar publishing ([73692dc](https://github.com/imadtg/TKUS-CE/commit/73692dc96b5b487983c7af6915c33f6df41f5d7c))\n* remove ci timeout ([6c85f92](https://github.com/imadtg/TKUS-CE/commit/6c85f92ae6038b5808e2e447c48e434f2cdf2e7d))\n* repair sequences/itemsets that are too long ([3be5c50](https://github.com/imadtg/TKUS-CE/commit/3be5c5059ed021b230b051b562b9ac6df3086512))\n* repair sequences/itemsets that are too long ([#18](https://github.com/imadtg/TKUS-CE/issues/18)) ([a0dd96a](https://github.com/imadtg/TKUS-CE/commit/a0dd96af8d7d3ff997cae635b685b2d08602aab9))\n* scan bounds of feasible solution itemset/sequence maximum sizes and enforce them ([858af53](https://github.com/imadtg/TKUS-CE/commit/858af53e7c304b974f39bb999ecaaa70041957bd))\n* scan bounds of feasible solution itemset/sequence maximum sizes and enforce them ([#5](https://github.com/imadtg/TKUS-CE/issues/5)) ([a6a1c02](https://github.com/imadtg/TKUS-CE/commit/a6a1c029c1ce2be7fa2007e41e426fc884a0823d))\n* seed the random processes in the algorithm ([3dabab2](https://github.com/imadtg/TKUS-CE/commit/3dabab295498ddc8e911247d767dcb0844b588e1))\n* seed the random processes in the algorithm ([#26](https://github.com/imadtg/TKUS-CE/issues/26)) ([4ad6a27](https://github.com/imadtg/TKUS-CE/commit/4ad6a27feb3d1e03e1e5f851a13a388f200fb309))\n* structure parameters in a dvc friendly way ([1260b00](https://github.com/imadtg/TKUS-CE/commit/1260b0014ee663cbdf00d6dbbeacc12dbacd2702))\n* structure parameters in a dvc friendly way ([#23](https://github.com/imadtg/TKUS-CE/issues/23)) ([56414b2](https://github.com/imadtg/TKUS-CE/commit/56414b273bfee85eb757b56de2b581e861098796))\n* tighter sampling and evaluation loop ([#39](https://github.com/imadtg/TKUS-CE/issues/39)) ([89692d2](https://github.com/imadtg/TKUS-CE/commit/89692d2ec47da35b334c5a015a5e4093066a448a))\n* validate model type param ([3e1740e](https://github.com/imadtg/TKUS-CE/commit/3e1740eab748498b876417336d42596713367168))\n* WIP cli interface ([ea4661b](https://github.com/imadtg/TKUS-CE/commit/ea4661b239bb6103f88f1b19c2e56370e52e1479))\n* WIP cli interface ([#33](https://github.com/imadtg/TKUS-CE/issues/33)) ([7469011](https://github.com/imadtg/TKUS-CE/commit/74690118ff06bd6f6fda230114884fa39ed05667))\n\n\n### Performance Improvements\n\n* actively prune items that get below the threshold during runtime ([#37](https://github.com/imadtg/TKUS-CE/issues/37)) ([749b8d2](https://github.com/imadtg/TKUS-CE/commit/749b8d2c6e8015fdb73c2e15449702740aaa0935))\n* calculate initial minimum utility using CUV ([#38](https://github.com/imadtg/TKUS-CE/issues/38)) ([c616b7c](https://github.com/imadtg/TKUS-CE/commit/c616b7c402e425df9523253684358dca6318bdb4))\n* fitness calculation caching ([#4](https://github.com/imadtg/TKUS-CE/issues/4)) ([5c048f9](https://github.com/imadtg/TKUS-CE/commit/5c048f9ad03875b967f55d0509124dc680ac811a))\n* implement a fitness cache ([059b4d6](https://github.com/imadtg/TKUS-CE/commit/059b4d62069c72a015e928e9c2e92bf76e2598db))\n* refactor loops over bitsets ([62d6cd9](https://github.com/imadtg/TKUS-CE/commit/62d6cd993dbdc8fc5e090e8bc5bbea5c081fe576))\n\n\n### BREAKING CHANGES\n\n* output file must now be specified explicitly!\n\nfeat: add AGENTS.md\n* output file must now be specified explicitly!\n\n\n\n"
  },
  "build_metadata": {
    "artifact": "tkus-ce-1.0.0.jar",
    "version": "1.0.0",
    "release_channel": "release",
    "source": "src/Main.java",
    "git_ref": "v1.0.0",
    "git_sha": "73692dc96b5b487983c7af6915c33f6df41f5d7c",
    "repository": "https://github.com/imadtg/TKUS-CE",
    "built_at_utc": "2026-03-12T11:30:04Z",
    "java_version": "openjdk version \"21.0.10\" 2026-01-20 LTS",
    "jbang_version": "0.137.0"
  }
}